{
  "text": "It seems like there might be an incomplete question or statement. If you're looking for information on the digital television services that Swisscom offers, the context mentions that Swisscom delivers a comprehensive selection of digital television channels and on-demand content. If this is not what you were looking for, could you please provide more details or clarify your question?",
  "duration": 25.733333333333334,
  "mouthCues": [
    {
      "start": 0.0,
      "end": 0.09453832965956374,
      "value": "X"
    },
    {
      "start": 0.09453832965956374,
      "end": 0.16071516042125836,
      "value": "I"
    },
    {
      "start": 0.16071516042125836,
      "end": 0.22689199118295297,
      "value": "T"
    },
    {
      "start": 0.22689199118295297,
      "end": 0.2930688219446476,
      "value": "X"
    },
    {
      "start": 0.2930688219446476,
      "end": 0.35924565270634223,
      "value": "S"
    },
    {
      "start": 0.35924565270634223,
      "end": 0.42542248346803685,
      "value": "E"
    },
    {
      "start": 0.42542248346803685,
      "end": 0.49159931422973147,
      "value": "E"
    },
    {
      "start": 0.49159931422973147,
      "end": 0.5577761449914261,
      "value": "X"
    },
    {
      "start": 0.5577761449914261,
      "end": 0.6239529757531208,
      "value": "S"
    },
    {
      "start": 0.6239529757531208,
      "end": 0.6901298065148155,
      "value": "X"
    },
    {
      "start": 0.6901298065148155,
      "end": 0.7563066372765102,
      "value": "X"
    },
    {
      "start": 0.7563066372765102,
      "end": 0.8224834680382048,
      "value": "I"
    },
    {
      "start": 0.8224834680382048,
      "end": 0.8886602987998995,
      "value": "K"
    },
    {
      "start": 0.8886602987998995,
      "end": 0.9548371295615942,
      "value": "E"
    },
    {
      "start": 0.9548371295615942,
      "end": 1.0210139603232888,
      "value": "X"
    },
    {
      "start": 1.0210139603232888,
      "end": 1.0871907910849834,
      "value": "T"
    },
    {
      "start": 1.0871907910849834,
      "end": 1.1533676218466782,
      "value": "T"
    },
    {
      "start": 1.1533676218466782,
      "end": 1.219544452608373,
      "value": "E"
    },
    {
      "start": 1.219544452608373,
      "end": 1.2857212833700675,
      "value": "R"
    },
    {
      "start": 1.2857212833700675,
      "end": 1.3518981141317623,
      "value": "E"
    },
    {
      "start": 1.3518981141317623,
      "end": 1.4180749448934569,
      "value": "X"
    },
    {
      "start": 1.4180749448934569,
      "end": 1.4842517756551517,
      "value": "X"
    },
    {
      "start": 1.4842517756551517,
      "end": 1.5504286064168462,
      "value": "I"
    },
    {
      "start": 1.5504286064168462,
      "end": 1.616605437178541,
      "value": "K"
    },
    {
      "start": 1.616605437178541,
      "end": 1.6827822679402356,
      "value": "T"
    },
    {
      "start": 1.6827822679402356,
      "end": 1.7489590987019303,
      "value": "T"
    },
    {
      "start": 1.7489590987019303,
      "end": 1.815135929463625,
      "value": "X"
    },
    {
      "start": 1.815135929463625,
      "end": 1.8813127602253197,
      "value": "B"
    },
    {
      "start": 1.8813127602253197,
      "end": 1.9474895909870142,
      "value": "E"
    },
    {
      "start": 1.9474895909870142,
      "end": 2.0136664217487086,
      "value": "X"
    },
    {
      "start": 2.0136664217487086,
      "end": 2.079843252510403,
      "value": "A"
    },
    {
      "start": 2.079843252510403,
      "end": 2.1460200832720977,
      "value": "N"
    },
    {
      "start": 2.1460200832720977,
      "end": 2.2121969140337923,
      "value": "X"
    },
    {
      "start": 2.2121969140337923,
      "end": 2.2783737447954864,
      "value": "I"
    },
    {
      "start": 2.2783737447954864,
      "end": 2.344550575557181,
      "value": "N"
    },
    {
      "start": 2.344550575557181,
      "end": 2.4107274063188755,
      "value": "X"
    },
    {
      "start": 2.4107274063188755,
      "end": 2.47690423708057,
      "value": "O"
    },
    {
      "start": 2.47690423708057,
      "end": 2.5430810678422646,
      "value": "X"
    },
    {
      "start": 2.5430810678422646,
      "end": 2.6092578986039587,
      "value": "B"
    },
    {
      "start": 2.6092578986039587,
      "end": 2.6754347293656533,
      "value": "X"
    },
    {
      "start": 2.6754347293656533,
      "end": 2.741611560127348,
      "value": "E"
    },
    {
      "start": 2.741611560127348,
      "end": 2.8077883908890424,
      "value": "T"
    },
    {
      "start": 2.8077883908890424,
      "end": 2.873965221650737,
      "value": "E"
    },
    {
      "start": 2.873965221650737,
      "end": 2.940142052412431,
      "value": "X"
    },
    {
      "start": 2.940142052412431,
      "end": 3.0063188831741257,
      "value": "X"
    },
    {
      "start": 3.0063188831741257,
      "end": 3.07249571393582,
      "value": "U"
    },
    {
      "start": 3.07249571393582,
      "end": 3.1386725446975148,
      "value": "E"
    },
    {
      "start": 3.1386725446975148,
      "end": 3.204849375459209,
      "value": "S"
    },
    {
      "start": 3.204849375459209,
      "end": 3.2710262062209035,
      "value": "T"
    },
    {
      "start": 3.2710262062209035,
      "end": 3.337203036982598,
      "value": "I"
    },
    {
      "start": 3.337203036982598,
      "end": 3.4033798677442926,
      "value": "O"
    },
    {
      "start": 3.4033798677442926,
      "end": 3.469556698505987,
      "value": "N"
    },
    {
      "start": 3.469556698505987,
      "end": 3.5357335292676813,
      "value": "X"
    },
    {
      "start": 3.5357335292676813,
      "end": 3.601910360029376,
      "value": "O"
    },
    {
      "start": 3.601910360029376,
      "end": 3.6680871907910704,
      "value": "R"
    },
    {
      "start": 3.6680871907910704,
      "end": 3.734264021552765,
      "value": "X"
    },
    {
      "start": 3.734264021552765,
      "end": 3.800440852314459,
      "value": "S"
    },
    {
      "start": 3.800440852314459,
      "end": 3.866617683076154,
      "value": "T"
    },
    {
      "start": 3.866617683076154,
      "end": 3.932794513837849,
      "value": "A"
    },
    {
      "start": 3.932794513837849,
      "end": 3.998971344599544,
      "value": "T"
    },
    {
      "start": 3.998971344599544,
      "end": 4.065148175361239,
      "value": "E"
    },
    {
      "start": 4.065148175361239,
      "end": 4.131325006122934,
      "value": "X"
    },
    {
      "start": 4.131325006122934,
      "end": 4.197501836884628,
      "value": "E"
    },
    {
      "start": 4.197501836884628,
      "end": 4.263678667646324,
      "value": "N"
    },
    {
      "start": 4.263678667646324,
      "end": 4.329855498408018,
      "value": "T"
    },
    {
      "start": 4.329855498408018,
      "end": 4.396032329169714,
      "value": "X"
    },
    {
      "start": 4.396032329169714,
      "end": 4.462209159931408,
      "value": "X"
    },
    {
      "start": 4.462209159931408,
      "end": 4.528385990693103,
      "value": "I"
    },
    {
      "start": 4.528385990693103,
      "end": 4.594562821454798,
      "value": "F"
    },
    {
      "start": 4.594562821454798,
      "end": 4.660739652216493,
      "value": "X"
    },
    {
      "start": 4.660739652216493,
      "end": 4.726916482978187,
      "value": "X"
    },
    {
      "start": 4.726916482978187,
      "end": 4.793093313739883,
      "value": "O"
    },
    {
      "start": 4.793093313739883,
      "end": 4.859270144501577,
      "value": "U"
    },
    {
      "start": 4.859270144501577,
      "end": 4.925446975263272,
      "value": "X"
    },
    {
      "start": 4.925446975263272,
      "end": 4.991623806024967,
      "value": "R"
    },
    {
      "start": 4.991623806024967,
      "end": 5.057800636786662,
      "value": "E"
    },
    {
      "start": 5.057800636786662,
      "end": 5.123977467548357,
      "value": "X"
    },
    {
      "start": 5.123977467548357,
      "end": 5.190154298310052,
      "value": "X"
    },
    {
      "start": 5.190154298310052,
      "end": 5.2563311290717465,
      "value": "O"
    },
    {
      "start": 5.2563311290717465,
      "end": 5.322507959833442,
      "value": "O"
    },
    {
      "start": 5.322507959833442,
      "end": 5.3886847905951365,
      "value": "K"
    },
    {
      "start": 5.3886847905951365,
      "end": 5.454861621356831,
      "value": "I"
    },
    {
      "start": 5.454861621356831,
      "end": 5.5210384521185265,
      "value": "N"
    },
    {
      "start": 5.5210384521185265,
      "end": 5.587215282880221,
      "value": "K"
    },
    {
      "start": 5.587215282880221,
      "end": 5.653392113641916,
      "value": "X"
    },
    {
      "start": 5.653392113641916,
      "end": 5.719568944403611,
      "value": "F"
    },
    {
      "start": 5.719568944403611,
      "end": 5.785745775165306,
      "value": "O"
    },
    {
      "start": 5.785745775165306,
      "end": 5.851922605927001,
      "value": "R"
    },
    {
      "start": 5.851922605927001,
      "end": 5.918099436688696,
      "value": "X"
    },
    {
      "start": 5.918099436688696,
      "end": 5.98427626745039,
      "value": "I"
    },
    {
      "start": 5.98427626745039,
      "end": 6.050453098212086,
      "value": "N"
    },
    {
      "start": 6.050453098212086,
      "end": 6.11662992897378,
      "value": "F"
    },
    {
      "start": 6.11662992897378,
      "end": 6.182806759735475,
      "value": "O"
    },
    {
      "start": 6.182806759735475,
      "end": 6.24898359049717,
      "value": "R"
    },
    {
      "start": 6.24898359049717,
      "end": 6.315160421258865,
      "value": "X"
    },
    {
      "start": 6.315160421258865,
      "end": 6.381337252020559,
      "value": "A"
    },
    {
      "start": 6.381337252020559,
      "end": 6.447514082782255,
      "value": "T"
    },
    {
      "start": 6.447514082782255,
      "end": 6.513690913543949,
      "value": "I"
    },
    {
      "start": 6.513690913543949,
      "end": 6.579867744305645,
      "value": "O"
    },
    {
      "start": 6.579867744305645,
      "end": 6.646044575067339,
      "value": "N"
    },
    {
      "start": 6.646044575067339,
      "end": 6.712221405829034,
      "value": "X"
    },
    {
      "start": 6.712221405829034,
      "end": 6.778398236590729,
      "value": "O"
    },
    {
      "start": 6.778398236590729,
      "end": 6.844575067352424,
      "value": "N"
    },
    {
      "start": 6.844575067352424,
      "end": 6.9107518981141185,
      "value": "X"
    },
    {
      "start": 6.9107518981141185,
      "end": 6.976928728875814,
      "value": "T"
    },
    {
      "start": 6.976928728875814,
      "end": 7.0431055596375085,
      "value": "T"
    },
    {
      "start": 7.0431055596375085,
      "end": 7.109282390399203,
      "value": "E"
    },
    {
      "start": 7.109282390399203,
      "end": 7.1754592211608985,
      "value": "X"
    },
    {
      "start": 7.1754592211608985,
      "end": 7.241636051922593,
      "value": "D"
    },
    {
      "start": 7.241636051922593,
      "end": 7.3078128826842885,
      "value": "I"
    },
    {
      "start": 7.3078128826842885,
      "end": 7.373989713445983,
      "value": "K"
    },
    {
      "start": 7.373989713445983,
      "end": 7.440166544207678,
      "value": "I"
    },
    {
      "start": 7.440166544207678,
      "end": 7.506343374969373,
      "value": "T"
    },
    {
      "start": 7.506343374969373,
      "end": 7.572520205731067,
      "value": "A"
    },
    {
      "start": 7.572520205731067,
      "end": 7.638697036492761,
      "value": "X"
    },
    {
      "start": 7.638697036492761,
      "end": 7.704873867254457,
      "value": "X"
    },
    {
      "start": 7.704873867254457,
      "end": 7.771050698016151,
      "value": "T"
    },
    {
      "start": 7.771050698016151,
      "end": 7.837227528777846,
      "value": "E"
    },
    {
      "start": 7.837227528777846,
      "end": 7.903404359539541,
      "value": "X"
    },
    {
      "start": 7.903404359539541,
      "end": 7.969581190301236,
      "value": "E"
    },
    {
      "start": 7.969581190301236,
      "end": 8.03575802106293,
      "value": "F"
    },
    {
      "start": 8.03575802106293,
      "end": 8.101934851824625,
      "value": "I"
    },
    {
      "start": 8.101934851824625,
      "end": 8.168111682586321,
      "value": "S"
    },
    {
      "start": 8.168111682586321,
      "end": 8.234288513348016,
      "value": "I"
    },
    {
      "start": 8.234288513348016,
      "end": 8.30046534410971,
      "value": "O"
    },
    {
      "start": 8.30046534410971,
      "end": 8.366642174871405,
      "value": "N"
    },
    {
      "start": 8.366642174871405,
      "end": 8.4328190056331,
      "value": "X"
    },
    {
      "start": 8.4328190056331,
      "end": 8.498995836394796,
      "value": "S"
    },
    {
      "start": 8.498995836394796,
      "end": 8.56517266715649,
      "value": "E"
    },
    {
      "start": 8.56517266715649,
      "end": 8.631349497918185,
      "value": "R"
    },
    {
      "start": 8.631349497918185,
      "end": 8.69752632867988,
      "value": "F"
    },
    {
      "start": 8.69752632867988,
      "end": 8.763703159441574,
      "value": "I"
    },
    {
      "start": 8.763703159441574,
      "end": 8.829879990203269,
      "value": "X"
    },
    {
      "start": 8.829879990203269,
      "end": 8.896056820964965,
      "value": "E"
    },
    {
      "start": 8.896056820964965,
      "end": 8.96223365172666,
      "value": "S"
    },
    {
      "start": 8.96223365172666,
      "end": 9.028410482488354,
      "value": "X"
    },
    {
      "start": 9.028410482488354,
      "end": 9.094587313250049,
      "value": "T"
    },
    {
      "start": 9.094587313250049,
      "end": 9.160764144011743,
      "value": "T"
    },
    {
      "start": 9.160764144011743,
      "end": 9.22694097477344,
      "value": "A"
    },
    {
      "start": 9.22694097477344,
      "end": 9.293117805535134,
      "value": "T"
    },
    {
      "start": 9.293117805535134,
      "end": 9.359294636296829,
      "value": "X"
    },
    {
      "start": 9.359294636296829,
      "end": 9.425471467058523,
      "value": "S"
    },
    {
      "start": 9.425471467058523,
      "end": 9.491648297820218,
      "value": "X"
    },
    {
      "start": 9.491648297820218,
      "end": 9.557825128581912,
      "value": "I"
    },
    {
      "start": 9.557825128581912,
      "end": 9.624001959343609,
      "value": "S"
    },
    {
      "start": 9.624001959343609,
      "end": 9.690178790105303,
      "value": "S"
    },
    {
      "start": 9.690178790105303,
      "end": 9.756355620866998,
      "value": "X"
    },
    {
      "start": 9.756355620866998,
      "end": 9.822532451628692,
      "value": "O"
    },
    {
      "start": 9.822532451628692,
      "end": 9.888709282390387,
      "value": "X"
    },
    {
      "start": 9.888709282390387,
      "end": 9.954886113152083,
      "value": "X"
    },
    {
      "start": 9.954886113152083,
      "end": 10.021062943913778,
      "value": "O"
    },
    {
      "start": 10.021062943913778,
      "end": 10.087239774675473,
      "value": "F"
    },
    {
      "start": 10.087239774675473,
      "end": 10.153416605437167,
      "value": "F"
    },
    {
      "start": 10.153416605437167,
      "end": 10.219593436198862,
      "value": "E"
    },
    {
      "start": 10.219593436198862,
      "end": 10.285770266960556,
      "value": "R"
    },
    {
      "start": 10.285770266960556,
      "end": 10.351947097722253,
      "value": "S"
    },
    {
      "start": 10.351947097722253,
      "end": 10.418123928483947,
      "value": "X"
    },
    {
      "start": 10.418123928483947,
      "end": 10.484300759245642,
      "value": "X"
    },
    {
      "start": 10.484300759245642,
      "end": 10.550477590007336,
      "value": "T"
    },
    {
      "start": 10.550477590007336,
      "end": 10.61665442076903,
      "value": "T"
    },
    {
      "start": 10.61665442076903,
      "end": 10.682831251530727,
      "value": "E"
    },
    {
      "start": 10.682831251530727,
      "end": 10.749008082292422,
      "value": "X"
    },
    {
      "start": 10.749008082292422,
      "end": 10.815184913054116,
      "value": "X"
    },
    {
      "start": 10.815184913054116,
      "end": 10.88136174381581,
      "value": "O"
    },
    {
      "start": 10.88136174381581,
      "end": 10.947538574577505,
      "value": "N"
    },
    {
      "start": 10.947538574577505,
      "end": 11.0137154053392,
      "value": "T"
    },
    {
      "start": 11.0137154053392,
      "end": 11.079892236100896,
      "value": "E"
    },
    {
      "start": 11.079892236100896,
      "end": 11.14606906686259,
      "value": "X"
    },
    {
      "start": 11.14606906686259,
      "end": 11.212245897624285,
      "value": "T"
    },
    {
      "start": 11.212245897624285,
      "end": 11.27842272838598,
      "value": "X"
    },
    {
      "start": 11.27842272838598,
      "end": 11.344599559147674,
      "value": "X"
    },
    {
      "start": 11.344599559147674,
      "end": 11.41077638990937,
      "value": "E"
    },
    {
      "start": 11.41077638990937,
      "end": 11.476953220671065,
      "value": "N"
    },
    {
      "start": 11.476953220671065,
      "end": 11.54313005143276,
      "value": "T"
    },
    {
      "start": 11.54313005143276,
      "end": 11.609306882194455,
      "value": "I"
    },
    {
      "start": 11.609306882194455,
      "end": 11.675483712956149,
      "value": "O"
    },
    {
      "start": 11.675483712956149,
      "end": 11.741660543717844,
      "value": "N"
    },
    {
      "start": 11.741660543717844,
      "end": 11.80783737447954,
      "value": "S"
    },
    {
      "start": 11.80783737447954,
      "end": 11.874014205241235,
      "value": "X"
    },
    {
      "start": 11.874014205241235,
      "end": 11.940191036002929,
      "value": "T"
    },
    {
      "start": 11.940191036002929,
      "end": 12.006367866764624,
      "value": "T"
    },
    {
      "start": 12.006367866764624,
      "end": 12.072544697526318,
      "value": "A"
    },
    {
      "start": 12.072544697526318,
      "end": 12.138721528288015,
      "value": "T"
    },
    {
      "start": 12.138721528288015,
      "end": 12.204898359049709,
      "value": "X"
    },
    {
      "start": 12.204898359049709,
      "end": 12.271075189811404,
      "value": "S"
    },
    {
      "start": 12.271075189811404,
      "end": 12.337252020573098,
      "value": "X"
    },
    {
      "start": 12.337252020573098,
      "end": 12.403428851334793,
      "value": "I"
    },
    {
      "start": 12.403428851334793,
      "end": 12.469605682096487,
      "value": "S"
    },
    {
      "start": 12.469605682096487,
      "end": 12.535782512858184,
      "value": "S"
    },
    {
      "start": 12.535782512858184,
      "end": 12.601959343619878,
      "value": "X"
    },
    {
      "start": 12.601959343619878,
      "end": 12.668136174381573,
      "value": "O"
    },
    {
      "start": 12.668136174381573,
      "end": 12.734313005143267,
      "value": "X"
    },
    {
      "start": 12.734313005143267,
      "end": 12.800489835904962,
      "value": "X"
    },
    {
      "start": 12.800489835904962,
      "end": 12.866666666666658,
      "value": "D"
    },
    {
      "start": 12.866666666666658,
      "end": 12.932843497428353,
      "value": "E"
    },
    {
      "start": 12.932843497428353,
      "end": 12.999020328190047,
      "value": "X"
    },
    {
      "start": 12.999020328190047,
      "end": 13.065197158951742,
      "value": "I"
    },
    {
      "start": 13.065197158951742,
      "end": 13.131373989713437,
      "value": "F"
    },
    {
      "start": 13.131373989713437,
      "end": 13.197550820475131,
      "value": "E"
    },
    {
      "start": 13.197550820475131,
      "end": 13.263727651236827,
      "value": "R"
    },
    {
      "start": 13.263727651236827,
      "end": 13.329904481998522,
      "value": "S"
    },
    {
      "start": 13.329904481998522,
      "end": 13.396081312760217,
      "value": "X"
    },
    {
      "start": 13.396081312760217,
      "end": 13.462258143521911,
      "value": "A"
    },
    {
      "start": 13.462258143521911,
      "end": 13.528434974283606,
      "value": "X"
    },
    {
      "start": 13.528434974283606,
      "end": 13.594611805045302,
      "value": "X"
    },
    {
      "start": 13.594611805045302,
      "end": 13.660788635806997,
      "value": "O"
    },
    {
      "start": 13.660788635806997,
      "end": 13.726965466568691,
      "value": "X"
    },
    {
      "start": 13.726965466568691,
      "end": 13.793142297330386,
      "value": "B"
    },
    {
      "start": 13.793142297330386,
      "end": 13.85931912809208,
      "value": "R"
    },
    {
      "start": 13.85931912809208,
      "end": 13.925495958853775,
      "value": "E"
    },
    {
      "start": 13.925495958853775,
      "end": 13.991672789615471,
      "value": "T"
    },
    {
      "start": 13.991672789615471,
      "end": 14.057849620377166,
      "value": "E"
    },
    {
      "start": 14.057849620377166,
      "end": 14.12402645113886,
      "value": "N"
    },
    {
      "start": 14.12402645113886,
      "end": 14.190203281900555,
      "value": "S"
    },
    {
      "start": 14.190203281900555,
      "end": 14.25638011266225,
      "value": "I"
    },
    {
      "start": 14.25638011266225,
      "end": 14.322556943423946,
      "value": "F"
    },
    {
      "start": 14.322556943423946,
      "end": 14.38873377418564,
      "value": "E"
    },
    {
      "start": 14.38873377418564,
      "end": 14.454910604947335,
      "value": "X"
    },
    {
      "start": 14.454910604947335,
      "end": 14.52108743570903,
      "value": "S"
    },
    {
      "start": 14.52108743570903,
      "end": 14.587264266470724,
      "value": "E"
    },
    {
      "start": 14.587264266470724,
      "end": 14.653441097232418,
      "value": "X"
    },
    {
      "start": 14.653441097232418,
      "end": 14.719617927994115,
      "value": "E"
    },
    {
      "start": 14.719617927994115,
      "end": 14.78579475875581,
      "value": "X"
    },
    {
      "start": 14.78579475875581,
      "end": 14.851971589517504,
      "value": "T"
    },
    {
      "start": 14.851971589517504,
      "end": 14.918148420279199,
      "value": "I"
    },
    {
      "start": 14.918148420279199,
      "end": 14.984325251040893,
      "value": "O"
    },
    {
      "start": 14.984325251040893,
      "end": 15.05050208180259,
      "value": "N"
    },
    {
      "start": 15.05050208180259,
      "end": 15.116678912564284,
      "value": "X"
    },
    {
      "start": 15.116678912564284,
      "end": 15.182855743325979,
      "value": "O"
    },
    {
      "start": 15.182855743325979,
      "end": 15.249032574087673,
      "value": "F"
    },
    {
      "start": 15.249032574087673,
      "end": 15.315209404849368,
      "value": "X"
    },
    {
      "start": 15.315209404849368,
      "end": 15.381386235611062,
      "value": "D"
    },
    {
      "start": 15.381386235611062,
      "end": 15.447563066372759,
      "value": "I"
    },
    {
      "start": 15.447563066372759,
      "end": 15.513739897134453,
      "value": "K"
    },
    {
      "start": 15.513739897134453,
      "end": 15.579916727896148,
      "value": "I"
    },
    {
      "start": 15.579916727896148,
      "end": 15.646093558657842,
      "value": "T"
    },
    {
      "start": 15.646093558657842,
      "end": 15.712270389419537,
      "value": "A"
    },
    {
      "start": 15.712270389419537,
      "end": 15.778447220181233,
      "value": "X"
    },
    {
      "start": 15.778447220181233,
      "end": 15.844624050942928,
      "value": "X"
    },
    {
      "start": 15.844624050942928,
      "end": 15.910800881704622,
      "value": "T"
    },
    {
      "start": 15.910800881704622,
      "end": 15.976977712466317,
      "value": "E"
    },
    {
      "start": 15.976977712466317,
      "end": 16.043154543228013,
      "value": "X"
    },
    {
      "start": 16.043154543228013,
      "end": 16.109331373989708,
      "value": "E"
    },
    {
      "start": 16.109331373989708,
      "end": 16.175508204751402,
      "value": "F"
    },
    {
      "start": 16.175508204751402,
      "end": 16.241685035513097,
      "value": "I"
    },
    {
      "start": 16.241685035513097,
      "end": 16.30786186627479,
      "value": "S"
    },
    {
      "start": 16.30786186627479,
      "end": 16.374038697036486,
      "value": "I"
    },
    {
      "start": 16.374038697036486,
      "end": 16.44021552779818,
      "value": "O"
    },
    {
      "start": 16.44021552779818,
      "end": 16.506392358559875,
      "value": "N"
    },
    {
      "start": 16.506392358559875,
      "end": 16.57256918932157,
      "value": "X"
    },
    {
      "start": 16.57256918932157,
      "end": 16.638746020083264,
      "value": "X"
    },
    {
      "start": 16.638746020083264,
      "end": 16.704922850844962,
      "value": "T"
    },
    {
      "start": 16.704922850844962,
      "end": 16.771099681606657,
      "value": "A"
    },
    {
      "start": 16.771099681606657,
      "end": 16.83727651236835,
      "value": "N"
    },
    {
      "start": 16.83727651236835,
      "end": 16.903453343130046,
      "value": "N"
    },
    {
      "start": 16.903453343130046,
      "end": 16.96963017389174,
      "value": "E"
    },
    {
      "start": 16.96963017389174,
      "end": 17.035807004653435,
      "value": "X"
    },
    {
      "start": 17.035807004653435,
      "end": 17.10198383541513,
      "value": "S"
    },
    {
      "start": 17.10198383541513,
      "end": 17.168160666176824,
      "value": "X"
    },
    {
      "start": 17.168160666176824,
      "end": 17.23433749693852,
      "value": "A"
    },
    {
      "start": 17.23433749693852,
      "end": 17.300514327700213,
      "value": "N"
    },
    {
      "start": 17.300514327700213,
      "end": 17.366691158461908,
      "value": "D"
    },
    {
      "start": 17.366691158461908,
      "end": 17.432867989223606,
      "value": "X"
    },
    {
      "start": 17.432867989223606,
      "end": 17.4990448199853,
      "value": "O"
    },
    {
      "start": 17.4990448199853,
      "end": 17.565221650746995,
      "value": "N"
    },
    {
      "start": 17.565221650746995,
      "end": 17.63139848150869,
      "value": "X"
    },
    {
      "start": 17.63139848150869,
      "end": 17.697575312270384,
      "value": "D"
    },
    {
      "start": 17.697575312270384,
      "end": 17.76375214303208,
      "value": "E"
    },
    {
      "start": 17.76375214303208,
      "end": 17.829928973793773,
      "value": "X"
    },
    {
      "start": 17.829928973793773,
      "end": 17.896105804555468,
      "value": "A"
    },
    {
      "start": 17.896105804555468,
      "end": 17.962282635317163,
      "value": "N"
    },
    {
      "start": 17.962282635317163,
      "end": 18.028459466078857,
      "value": "D"
    },
    {
      "start": 18.028459466078857,
      "end": 18.09463629684055,
      "value": "X"
    },
    {
      "start": 18.09463629684055,
      "end": 18.16081312760225,
      "value": "X"
    },
    {
      "start": 18.16081312760225,
      "end": 18.226989958363944,
      "value": "O"
    },
    {
      "start": 18.226989958363944,
      "end": 18.29316678912564,
      "value": "N"
    },
    {
      "start": 18.29316678912564,
      "end": 18.359343619887333,
      "value": "T"
    },
    {
      "start": 18.359343619887333,
      "end": 18.425520450649028,
      "value": "E"
    },
    {
      "start": 18.425520450649028,
      "end": 18.491697281410723,
      "value": "N"
    },
    {
      "start": 18.491697281410723,
      "end": 18.557874112172417,
      "value": "T"
    },
    {
      "start": 18.557874112172417,
      "end": 18.62405094293411,
      "value": "X"
    },
    {
      "start": 18.62405094293411,
      "end": 18.690227773695806,
      "value": "X"
    },
    {
      "start": 18.690227773695806,
      "end": 18.7564046044575,
      "value": "I"
    },
    {
      "start": 18.7564046044575,
      "end": 18.822581435219195,
      "value": "F"
    },
    {
      "start": 18.822581435219195,
      "end": 18.888758265980893,
      "value": "X"
    },
    {
      "start": 18.888758265980893,
      "end": 18.954935096742588,
      "value": "T"
    },
    {
      "start": 18.954935096742588,
      "end": 19.021111927504283,
      "value": "T"
    },
    {
      "start": 19.021111927504283,
      "end": 19.087288758265977,
      "value": "I"
    },
    {
      "start": 19.087288758265977,
      "end": 19.15346558902767,
      "value": "S"
    },
    {
      "start": 19.15346558902767,
      "end": 19.219642419789366,
      "value": "X"
    },
    {
      "start": 19.219642419789366,
      "end": 19.28581925055106,
      "value": "I"
    },
    {
      "start": 19.28581925055106,
      "end": 19.351996081312755,
      "value": "S"
    },
    {
      "start": 19.351996081312755,
      "end": 19.41817291207445,
      "value": "X"
    },
    {
      "start": 19.41817291207445,
      "end": 19.484349742836145,
      "value": "N"
    },
    {
      "start": 19.484349742836145,
      "end": 19.55052657359784,
      "value": "O"
    },
    {
      "start": 19.55052657359784,
      "end": 19.616703404359537,
      "value": "T"
    },
    {
      "start": 19.616703404359537,
      "end": 19.68288023512123,
      "value": "X"
    },
    {
      "start": 19.68288023512123,
      "end": 19.749057065882926,
      "value": "X"
    },
    {
      "start": 19.749057065882926,
      "end": 19.81523389664462,
      "value": "T"
    },
    {
      "start": 19.81523389664462,
      "end": 19.881410727406315,
      "value": "A"
    },
    {
      "start": 19.881410727406315,
      "end": 19.94758755816801,
      "value": "T"
    },
    {
      "start": 19.94758755816801,
      "end": 20.013764388929705,
      "value": "X"
    },
    {
      "start": 20.013764388929705,
      "end": 20.0799412196914,
      "value": "X"
    },
    {
      "start": 20.0799412196914,
      "end": 20.146118050453094,
      "value": "O"
    },
    {
      "start": 20.146118050453094,
      "end": 20.21229488121479,
      "value": "U"
    },
    {
      "start": 20.21229488121479,
      "end": 20.278471711976483,
      "value": "X"
    },
    {
      "start": 20.278471711976483,
      "end": 20.34464854273818,
      "value": "X"
    },
    {
      "start": 20.34464854273818,
      "end": 20.410825373499875,
      "value": "E"
    },
    {
      "start": 20.410825373499875,
      "end": 20.47700220426157,
      "value": "R"
    },
    {
      "start": 20.47700220426157,
      "end": 20.543179035023265,
      "value": "E"
    },
    {
      "start": 20.543179035023265,
      "end": 20.60935586578496,
      "value": "X"
    },
    {
      "start": 20.60935586578496,
      "end": 20.675532696546654,
      "value": "X"
    },
    {
      "start": 20.675532696546654,
      "end": 20.74170952730835,
      "value": "O"
    },
    {
      "start": 20.74170952730835,
      "end": 20.807886358070043,
      "value": "O"
    },
    {
      "start": 20.807886358070043,
      "end": 20.874063188831737,
      "value": "K"
    },
    {
      "start": 20.874063188831737,
      "end": 20.940240019593432,
      "value": "I"
    },
    {
      "start": 20.940240019593432,
      "end": 21.006416850355127,
      "value": "N"
    },
    {
      "start": 21.006416850355127,
      "end": 21.072593681116825,
      "value": "K"
    },
    {
      "start": 21.072593681116825,
      "end": 21.13877051187852,
      "value": "X"
    },
    {
      "start": 21.13877051187852,
      "end": 21.204947342640214,
      "value": "F"
    },
    {
      "start": 21.204947342640214,
      "end": 21.27112417340191,
      "value": "O"
    },
    {
      "start": 21.27112417340191,
      "end": 21.337301004163603,
      "value": "R"
    },
    {
      "start": 21.337301004163603,
      "end": 21.403477834925297,
      "value": "X"
    },
    {
      "start": 21.403477834925297,
      "end": 21.469654665686992,
      "value": "X"
    },
    {
      "start": 21.469654665686992,
      "end": 21.535831496448687,
      "value": "X"
    },
    {
      "start": 21.535831496448687,
      "end": 21.60200832721038,
      "value": "O"
    },
    {
      "start": 21.60200832721038,
      "end": 21.668185157972076,
      "value": "U"
    },
    {
      "start": 21.668185157972076,
      "end": 21.73436198873377,
      "value": "X"
    },
    {
      "start": 21.73436198873377,
      "end": 21.80053881949547,
      "value": "D"
    },
    {
      "start": 21.80053881949547,
      "end": 21.866715650257163,
      "value": "X"
    },
    {
      "start": 21.866715650257163,
      "end": 21.932892481018857,
      "value": "X"
    },
    {
      "start": 21.932892481018857,
      "end": 21.999069311780552,
      "value": "O"
    },
    {
      "start": 21.999069311780552,
      "end": 22.065246142542247,
      "value": "U"
    },
    {
      "start": 22.065246142542247,
      "end": 22.13142297330394,
      "value": "X"
    },
    {
      "start": 22.13142297330394,
      "end": 22.197599804065636,
      "value": "B"
    },
    {
      "start": 22.197599804065636,
      "end": 22.26377663482733,
      "value": "X"
    },
    {
      "start": 22.26377663482733,
      "end": 22.329953465589025,
      "value": "E"
    },
    {
      "start": 22.329953465589025,
      "end": 22.39613029635072,
      "value": "A"
    },
    {
      "start": 22.39613029635072,
      "end": 22.462307127112414,
      "value": "S"
    },
    {
      "start": 22.462307127112414,
      "end": 22.528483957874112,
      "value": "E"
    },
    {
      "start": 22.528483957874112,
      "end": 22.594660788635807,
      "value": "X"
    },
    {
      "start": 22.594660788635807,
      "end": 22.6608376193975,
      "value": "B"
    },
    {
      "start": 22.6608376193975,
      "end": 22.727014450159196,
      "value": "R"
    },
    {
      "start": 22.727014450159196,
      "end": 22.79319128092089,
      "value": "O"
    },
    {
      "start": 22.79319128092089,
      "end": 22.859368111682585,
      "value": "F"
    },
    {
      "start": 22.859368111682585,
      "end": 22.92554494244428,
      "value": "I"
    },
    {
      "start": 22.92554494244428,
      "end": 22.991721773205974,
      "value": "D"
    },
    {
      "start": 22.991721773205974,
      "end": 23.05789860396767,
      "value": "E"
    },
    {
      "start": 23.05789860396767,
      "end": 23.124075434729363,
      "value": "X"
    },
    {
      "start": 23.124075434729363,
      "end": 23.190252265491058,
      "value": "X"
    },
    {
      "start": 23.190252265491058,
      "end": 23.256429096252756,
      "value": "O"
    },
    {
      "start": 23.256429096252756,
      "end": 23.32260592701445,
      "value": "R"
    },
    {
      "start": 23.32260592701445,
      "end": 23.388782757776145,
      "value": "E"
    },
    {
      "start": 23.388782757776145,
      "end": 23.45495958853784,
      "value": "X"
    },
    {
      "start": 23.45495958853784,
      "end": 23.521136419299534,
      "value": "D"
    },
    {
      "start": 23.521136419299534,
      "end": 23.58731325006123,
      "value": "E"
    },
    {
      "start": 23.58731325006123,
      "end": 23.653490080822923,
      "value": "T"
    },
    {
      "start": 23.653490080822923,
      "end": 23.719666911584618,
      "value": "A"
    },
    {
      "start": 23.719666911584618,
      "end": 23.785843742346312,
      "value": "I"
    },
    {
      "start": 23.785843742346312,
      "end": 23.852020573108007,
      "value": "X"
    },
    {
      "start": 23.852020573108007,
      "end": 23.9181974038697,
      "value": "S"
    },
    {
      "start": 23.9181974038697,
      "end": 23.9843742346314,
      "value": "X"
    },
    {
      "start": 23.9843742346314,
      "end": 24.050551065393094,
      "value": "O"
    },
    {
      "start": 24.050551065393094,
      "end": 24.11672789615479,
      "value": "R"
    },
    {
      "start": 24.11672789615479,
      "end": 24.182904726916483,
      "value": "X"
    },
    {
      "start": 24.182904726916483,
      "end": 24.249081557678178,
      "value": "X"
    },
    {
      "start": 24.249081557678178,
      "end": 24.315258388439872,
      "value": "X"
    },
    {
      "start": 24.315258388439872,
      "end": 24.381435219201567,
      "value": "A"
    },
    {
      "start": 24.381435219201567,
      "end": 24.44761204996326,
      "value": "R"
    },
    {
      "start": 24.44761204996326,
      "end": 24.513788880724956,
      "value": "I"
    },
    {
      "start": 24.513788880724956,
      "end": 24.57996571148665,
      "value": "F"
    },
    {
      "start": 24.57996571148665,
      "end": 24.646142542248345,
      "value": "X"
    },
    {
      "start": 24.646142542248345,
      "end": 24.712319373010043,
      "value": "X"
    },
    {
      "start": 24.712319373010043,
      "end": 24.778496203771738,
      "value": "X"
    },
    {
      "start": 24.778496203771738,
      "end": 24.844673034533432,
      "value": "O"
    },
    {
      "start": 24.844673034533432,
      "end": 24.910849865295127,
      "value": "U"
    },
    {
      "start": 24.910849865295127,
      "end": 24.97702669605682,
      "value": "R"
    },
    {
      "start": 24.97702669605682,
      "end": 25.043203526818516,
      "value": "X"
    },
    {
      "start": 25.043203526818516,
      "end": 25.10938035758021,
      "value": "X"
    },
    {
      "start": 25.10938035758021,
      "end": 25.175557188341905,
      "value": "U"
    },
    {
      "start": 25.175557188341905,
      "end": 25.2417340191036,
      "value": "E"
    },
    {
      "start": 25.2417340191036,
      "end": 25.307910849865294,
      "value": "S"
    },
    {
      "start": 25.307910849865294,
      "end": 25.37408768062699,
      "value": "T"
    },
    {
      "start": 25.37408768062699,
      "end": 25.440264511388687,
      "value": "I"
    },
    {
      "start": 25.440264511388687,
      "end": 25.50644134215038,
      "value": "O"
    },
    {
      "start": 25.50644134215038,
      "end": 25.572618172912076,
      "value": "N"
    },
    {
      "start": 25.572618172912076,
      "end": 25.63879500367377,
      "value": "X"
    },
    {
      "start": 25.63879500367377,
      "end": 25.733333333333334,
      "value": "X"
    }
  ]
}