{
  "metadata": {
    "soundFile": "C:\\Users\\Dell\\Desktop\\AVATAR-BOT-latest\\audio\\a49b61eb42c44cffb677469a9d9a0346.ogg",
    "duration": 7.48
  },
  "mouthCues": [
    { "start": 0.00, "end": 0.04, "value": "X" },
    { "start": 0.04, "end": 0.11, "value": "C" },
    { "start": 0.11, "end": 0.32, "value": "E" },
    { "start": 0.32, "end": 0.39, "value": "F" },
    { "start": 0.39, "end": 0.61, "value": "B" },
    { "start": 0.61, "end": 0.68, "value": "C" },
    { "start": 0.68, "end": 0.75, "value": "B" },
    { "start": 0.75, "end": 0.83, "value": "A" },
    { "start": 0.83, "end": 1.04, "value": "B" },
    { "start": 1.04, "end": 1.11, "value": "G" },
    { "start": 1.11, "end": 1.18, "value": "E" },
    { "start": 1.18, "end": 1.32, "value": "F" },
    { "start": 1.32, "end": 1.39, "value": "C" },
    { "start": 1.39, "end": 1.46, "value": "H" },
    { "start": 1.46, "end": 2.02, "value": "B" },
    { "start": 2.02, "end": 2.09, "value": "E" },
    { "start": 2.09, "end": 2.16, "value": "C" },
    { "start": 2.16, "end": 2.23, "value": "E" },
    { "start": 2.23, "end": 2.44, "value": "C" },
    { "start": 2.44, "end": 2.58, "value": "G" },
    { "start": 2.58, "end": 3.31, "value": "B" },
    { "start": 3.31, "end": 3.40, "value": "A" },
    { "start": 3.40, "end": 3.47, "value": "C" },
    { "start": 3.47, "end": 3.79, "value": "B" },
    { "start": 3.79, "end": 3.83, "value": "C" },
    { "start": 3.83, "end": 3.87, "value": "B" },
    { "start": 3.87, "end": 3.95, "value": "A" },
    { "start": 3.95, "end": 4.51, "value": "B" },
    { "start": 4.51, "end": 4.58, "value": "F" },
    { "start": 4.58, "end": 4.72, "value": "C" },
    { "start": 4.72, "end": 4.80, "value": "A" },
    { "start": 4.80, "end": 5.05, "value": "F" },
    { "start": 5.05, "end": 5.65, "value": "X" },
    { "start": 5.65, "end": 6.03, "value": "C" },
    { "start": 6.03, "end": 6.24, "value": "B" },
    { "start": 6.24, "end": 6.45, "value": "F" },
    { "start": 6.45, "end": 6.59, "value": "B" },
    { "start": 6.59, "end": 6.73, "value": "C" },
    { "start": 6.73, "end": 6.80, "value": "B" },
    { "start": 6.80, "end": 7.48, "value": "X" }
  ]
}
