{
  "text": "Yes, Swisscom offers 5G. The company launched its 5G network in April 2019, positioning Switzerland among the first countries to adopt this technology.",
  "duration": 10.066666666666666,
  "mouthCues": [
    {
      "start": 0.0,
      "end": 0.09346951408232726,
      "value": "X"
    },
    {
      "start": 0.09346951408232726,
      "end": 0.15889817393995634,
      "value": "X"
    },
    {
      "start": 0.15889817393995634,
      "end": 0.22432683379758542,
      "value": "E"
    },
    {
      "start": 0.22432683379758542,
      "end": 0.2897554936552145,
      "value": "S"
    },
    {
      "start": 0.2897554936552145,
      "end": 0.3551841535128436,
      "value": "X"
    },
    {
      "start": 0.3551841535128436,
      "end": 0.4206128133704727,
      "value": "X"
    },
    {
      "start": 0.4206128133704727,
      "end": 0.48604147322810176,
      "value": "S"
    },
    {
      "start": 0.48604147322810176,
      "end": 0.5514701330857309,
      "value": "X"
    },
    {
      "start": 0.5514701330857309,
      "end": 0.61689879294336,
      "value": "I"
    },
    {
      "start": 0.61689879294336,
      "end": 0.6823274528009892,
      "value": "S"
    },
    {
      "start": 0.6823274528009892,
      "end": 0.7477561126586183,
      "value": "S"
    },
    {
      "start": 0.7477561126586183,
      "end": 0.8131847725162474,
      "value": "X"
    },
    {
      "start": 0.8131847725162474,
      "end": 0.8786134323738766,
      "value": "O"
    },
    {
      "start": 0.8786134323738766,
      "end": 0.9440420922315057,
      "value": "X"
    },
    {
      "start": 0.9440420922315057,
      "end": 1.0094707520891348,
      "value": "X"
    },
    {
      "start": 1.0094707520891348,
      "end": 1.0748994119467639,
      "value": "O"
    },
    {
      "start": 1.0748994119467639,
      "end": 1.140328071804393,
      "value": "F"
    },
    {
      "start": 1.140328071804393,
      "end": 1.2057567316620221,
      "value": "F"
    },
    {
      "start": 1.2057567316620221,
      "end": 1.2711853915196514,
      "value": "E"
    },
    {
      "start": 1.2711853915196514,
      "end": 1.3366140513772804,
      "value": "R"
    },
    {
      "start": 1.3366140513772804,
      "end": 1.4020427112349096,
      "value": "S"
    },
    {
      "start": 1.4020427112349096,
      "end": 1.4674713710925387,
      "value": "X"
    },
    {
      "start": 1.4674713710925387,
      "end": 1.532900030950168,
      "value": "X"
    },
    {
      "start": 1.532900030950168,
      "end": 1.5983286908077972,
      "value": "K"
    },
    {
      "start": 1.5983286908077972,
      "end": 1.6637573506654262,
      "value": "X"
    },
    {
      "start": 1.6637573506654262,
      "end": 1.7291860105230554,
      "value": "X"
    },
    {
      "start": 1.7291860105230554,
      "end": 1.7946146703806845,
      "value": "T"
    },
    {
      "start": 1.7946146703806845,
      "end": 1.8600433302383137,
      "value": "T"
    },
    {
      "start": 1.8600433302383137,
      "end": 1.9254719900959427,
      "value": "E"
    },
    {
      "start": 1.9254719900959427,
      "end": 1.9909006499535717,
      "value": "X"
    },
    {
      "start": 1.9909006499535717,
      "end": 2.0563293098112005,
      "value": "X"
    },
    {
      "start": 2.0563293098112005,
      "end": 2.1217579696688293,
      "value": "O"
    },
    {
      "start": 2.1217579696688293,
      "end": 2.1871866295264586,
      "value": "X"
    },
    {
      "start": 2.1871866295264586,
      "end": 2.2526152893840874,
      "value": "B"
    },
    {
      "start": 2.2526152893840874,
      "end": 2.318043949241716,
      "value": "A"
    },
    {
      "start": 2.318043949241716,
      "end": 2.3834726090993454,
      "value": "N"
    },
    {
      "start": 2.3834726090993454,
      "end": 2.4489012689569742,
      "value": "X"
    },
    {
      "start": 2.4489012689569742,
      "end": 2.514329928814603,
      "value": "X"
    },
    {
      "start": 2.514329928814603,
      "end": 2.579758588672232,
      "value": "X"
    },
    {
      "start": 2.579758588672232,
      "end": 2.645187248529861,
      "value": "A"
    },
    {
      "start": 2.645187248529861,
      "end": 2.71061590838749,
      "value": "U"
    },
    {
      "start": 2.71061590838749,
      "end": 2.7760445682451187,
      "value": "N"
    },
    {
      "start": 2.7760445682451187,
      "end": 2.841473228102748,
      "value": "X"
    },
    {
      "start": 2.841473228102748,
      "end": 2.9069018879603767,
      "value": "T"
    },
    {
      "start": 2.9069018879603767,
      "end": 2.9723305478180055,
      "value": "E"
    },
    {
      "start": 2.9723305478180055,
      "end": 3.0377592076756343,
      "value": "D"
    },
    {
      "start": 3.0377592076756343,
      "end": 3.1031878675332636,
      "value": "X"
    },
    {
      "start": 3.1031878675332636,
      "end": 3.1686165273908924,
      "value": "I"
    },
    {
      "start": 3.1686165273908924,
      "end": 3.234045187248521,
      "value": "T"
    },
    {
      "start": 3.234045187248521,
      "end": 3.2994738471061504,
      "value": "S"
    },
    {
      "start": 3.2994738471061504,
      "end": 3.3649025069637792,
      "value": "X"
    },
    {
      "start": 3.3649025069637792,
      "end": 3.430331166821408,
      "value": "X"
    },
    {
      "start": 3.430331166821408,
      "end": 3.495759826679037,
      "value": "K"
    },
    {
      "start": 3.495759826679037,
      "end": 3.561188486536666,
      "value": "X"
    },
    {
      "start": 3.561188486536666,
      "end": 3.626617146394295,
      "value": "N"
    },
    {
      "start": 3.626617146394295,
      "end": 3.6920458062519237,
      "value": "E"
    },
    {
      "start": 3.6920458062519237,
      "end": 3.757474466109553,
      "value": "T"
    },
    {
      "start": 3.757474466109553,
      "end": 3.822903125967182,
      "value": "X"
    },
    {
      "start": 3.822903125967182,
      "end": 3.8883317858248114,
      "value": "O"
    },
    {
      "start": 3.8883317858248114,
      "end": 3.9537604456824407,
      "value": "R"
    },
    {
      "start": 3.9537604456824407,
      "end": 4.01918910554007,
      "value": "K"
    },
    {
      "start": 4.01918910554007,
      "end": 4.0846177653977,
      "value": "X"
    },
    {
      "start": 4.0846177653977,
      "end": 4.150046425255328,
      "value": "I"
    },
    {
      "start": 4.150046425255328,
      "end": 4.215475085112958,
      "value": "N"
    },
    {
      "start": 4.215475085112958,
      "end": 4.280903744970588,
      "value": "X"
    },
    {
      "start": 4.280903744970588,
      "end": 4.346332404828217,
      "value": "A"
    },
    {
      "start": 4.346332404828217,
      "end": 4.411761064685846,
      "value": "B"
    },
    {
      "start": 4.411761064685846,
      "end": 4.477189724543475,
      "value": "R"
    },
    {
      "start": 4.477189724543475,
      "end": 4.542618384401105,
      "value": "I"
    },
    {
      "start": 4.542618384401105,
      "end": 4.6080470442587345,
      "value": "X"
    },
    {
      "start": 4.6080470442587345,
      "end": 4.673475704116363,
      "value": "X"
    },
    {
      "start": 4.673475704116363,
      "end": 4.738904363973993,
      "value": "X"
    },
    {
      "start": 4.738904363973993,
      "end": 4.804333023831623,
      "value": "X"
    },
    {
      "start": 4.804333023831623,
      "end": 4.869761683689251,
      "value": "X"
    },
    {
      "start": 4.869761683689251,
      "end": 4.935190343546881,
      "value": "X"
    },
    {
      "start": 4.935190343546881,
      "end": 5.00061900340451,
      "value": "X"
    },
    {
      "start": 5.00061900340451,
      "end": 5.06604766326214,
      "value": "X"
    },
    {
      "start": 5.06604766326214,
      "end": 5.131476323119769,
      "value": "B"
    },
    {
      "start": 5.131476323119769,
      "end": 5.196904982977398,
      "value": "O"
    },
    {
      "start": 5.196904982977398,
      "end": 5.262333642835028,
      "value": "S"
    },
    {
      "start": 5.262333642835028,
      "end": 5.327762302692657,
      "value": "I"
    },
    {
      "start": 5.327762302692657,
      "end": 5.393190962550286,
      "value": "T"
    },
    {
      "start": 5.393190962550286,
      "end": 5.458619622407916,
      "value": "I"
    },
    {
      "start": 5.458619622407916,
      "end": 5.524048282265545,
      "value": "O"
    },
    {
      "start": 5.524048282265545,
      "end": 5.5894769421231745,
      "value": "N"
    },
    {
      "start": 5.5894769421231745,
      "end": 5.654905601980803,
      "value": "I"
    },
    {
      "start": 5.654905601980803,
      "end": 5.720334261838433,
      "value": "N"
    },
    {
      "start": 5.720334261838433,
      "end": 5.785762921696063,
      "value": "K"
    },
    {
      "start": 5.785762921696063,
      "end": 5.8511915815536915,
      "value": "X"
    },
    {
      "start": 5.8511915815536915,
      "end": 5.916620241411321,
      "value": "S"
    },
    {
      "start": 5.916620241411321,
      "end": 5.982048901268951,
      "value": "X"
    },
    {
      "start": 5.982048901268951,
      "end": 6.04747756112658,
      "value": "I"
    },
    {
      "start": 6.04747756112658,
      "end": 6.112906220984209,
      "value": "T"
    },
    {
      "start": 6.112906220984209,
      "end": 6.178334880841838,
      "value": "S"
    },
    {
      "start": 6.178334880841838,
      "end": 6.243763540699468,
      "value": "E"
    },
    {
      "start": 6.243763540699468,
      "end": 6.3091922005570975,
      "value": "R"
    },
    {
      "start": 6.3091922005570975,
      "end": 6.374620860414726,
      "value": "X"
    },
    {
      "start": 6.374620860414726,
      "end": 6.440049520272356,
      "value": "A"
    },
    {
      "start": 6.440049520272356,
      "end": 6.505478180129985,
      "value": "N"
    },
    {
      "start": 6.505478180129985,
      "end": 6.5709068399876145,
      "value": "D"
    },
    {
      "start": 6.5709068399876145,
      "end": 6.636335499845244,
      "value": "X"
    },
    {
      "start": 6.636335499845244,
      "end": 6.701764159702873,
      "value": "A"
    },
    {
      "start": 6.701764159702873,
      "end": 6.767192819560503,
      "value": "X"
    },
    {
      "start": 6.767192819560503,
      "end": 6.8326214794181315,
      "value": "O"
    },
    {
      "start": 6.8326214794181315,
      "end": 6.898050139275761,
      "value": "N"
    },
    {
      "start": 6.898050139275761,
      "end": 6.963478799133391,
      "value": "K"
    },
    {
      "start": 6.963478799133391,
      "end": 7.02890745899102,
      "value": "X"
    },
    {
      "start": 7.02890745899102,
      "end": 7.094336118848649,
      "value": "T"
    },
    {
      "start": 7.094336118848649,
      "end": 7.159764778706279,
      "value": "T"
    },
    {
      "start": 7.159764778706279,
      "end": 7.225193438563908,
      "value": "E"
    },
    {
      "start": 7.225193438563908,
      "end": 7.2906220984215375,
      "value": "X"
    },
    {
      "start": 7.2906220984215375,
      "end": 7.356050758279166,
      "value": "F"
    },
    {
      "start": 7.356050758279166,
      "end": 7.421479418136796,
      "value": "I"
    },
    {
      "start": 7.421479418136796,
      "end": 7.486908077994425,
      "value": "R"
    },
    {
      "start": 7.486908077994425,
      "end": 7.552336737852054,
      "value": "S"
    },
    {
      "start": 7.552336737852054,
      "end": 7.617765397709683,
      "value": "T"
    },
    {
      "start": 7.617765397709683,
      "end": 7.683194057567312,
      "value": "X"
    },
    {
      "start": 7.683194057567312,
      "end": 7.748622717424942,
      "value": "X"
    },
    {
      "start": 7.748622717424942,
      "end": 7.8140513772825715,
      "value": "O"
    },
    {
      "start": 7.8140513772825715,
      "end": 7.8794800371402,
      "value": "U"
    },
    {
      "start": 7.8794800371402,
      "end": 7.94490869699783,
      "value": "N"
    },
    {
      "start": 7.94490869699783,
      "end": 8.010337356855459,
      "value": "T"
    },
    {
      "start": 8.010337356855459,
      "end": 8.07576601671309,
      "value": "R"
    },
    {
      "start": 8.07576601671309,
      "end": 8.141194676570718,
      "value": "I"
    },
    {
      "start": 8.141194676570718,
      "end": 8.206623336428347,
      "value": "E"
    },
    {
      "start": 8.206623336428347,
      "end": 8.272051996285976,
      "value": "S"
    },
    {
      "start": 8.272051996285976,
      "end": 8.337480656143606,
      "value": "X"
    },
    {
      "start": 8.337480656143606,
      "end": 8.402909316001235,
      "value": "T"
    },
    {
      "start": 8.402909316001235,
      "end": 8.468337975858864,
      "value": "O"
    },
    {
      "start": 8.468337975858864,
      "end": 8.533766635716495,
      "value": "X"
    },
    {
      "start": 8.533766635716495,
      "end": 8.599195295574123,
      "value": "A"
    },
    {
      "start": 8.599195295574123,
      "end": 8.664623955431752,
      "value": "D"
    },
    {
      "start": 8.664623955431752,
      "end": 8.730052615289383,
      "value": "O"
    },
    {
      "start": 8.730052615289383,
      "end": 8.795481275147012,
      "value": "B"
    },
    {
      "start": 8.795481275147012,
      "end": 8.86090993500464,
      "value": "T"
    },
    {
      "start": 8.86090993500464,
      "end": 8.92633859486227,
      "value": "X"
    },
    {
      "start": 8.92633859486227,
      "end": 8.9917672547199,
      "value": "T"
    },
    {
      "start": 8.9917672547199,
      "end": 9.057195914577528,
      "value": "T"
    },
    {
      "start": 9.057195914577528,
      "end": 9.122624574435157,
      "value": "I"
    },
    {
      "start": 9.122624574435157,
      "end": 9.188053234292788,
      "value": "S"
    },
    {
      "start": 9.188053234292788,
      "end": 9.253481894150417,
      "value": "X"
    },
    {
      "start": 9.253481894150417,
      "end": 9.318910554008045,
      "value": "T"
    },
    {
      "start": 9.318910554008045,
      "end": 9.384339213865676,
      "value": "E"
    },
    {
      "start": 9.384339213865676,
      "end": 9.449767873723305,
      "value": "X"
    },
    {
      "start": 9.449767873723305,
      "end": 9.515196533580934,
      "value": "T"
    },
    {
      "start": 9.515196533580934,
      "end": 9.580625193438564,
      "value": "N"
    },
    {
      "start": 9.580625193438564,
      "end": 9.646053853296193,
      "value": "O"
    },
    {
      "start": 9.646053853296193,
      "end": 9.711482513153822,
      "value": "X"
    },
    {
      "start": 9.711482513153822,
      "end": 9.77691117301145,
      "value": "O"
    },
    {
      "start": 9.77691117301145,
      "end": 9.842339832869081,
      "value": "K"
    },
    {
      "start": 9.842339832869081,
      "end": 9.90776849272671,
      "value": "X"
    },
    {
      "start": 9.90776849272671,
      "end": 9.973197152584339,
      "value": "X"
    },
    {
      "start": 9.973197152584339,
      "end": 10.066666666666666,
      "value": "X"
    }
  ]
}